_estraiernative.so
hypy/__init__.py
hypy/_version.py
hypy/lib.py
hypy/test_lib.py
Hypy-1.0.1.dist-info/METADATA
Hypy-1.0.1.dist-info/WHEEL
Hypy-1.0.1.dist-info/top_level.txt
Hypy-1.0.1.dist-info/RECORD
