Metadata-Version: 2.1
Name: Hypy
Version: 1.0.1
Summary: Pythonic wrapper for Hyper Estraier
Home-page: https://github.com/corydodt/Hypy
Author: Yusuke YOSHIDA
Author-email: usk@nrgate.jp
Maintainer: Cory Dodt
Maintainer-email: pypi@spam.goonmill.org
License: UNKNOWN
Download-URL: https://github.com/corydodt/Hypy/archive/release-1.0.1.tar.gz
Platform: UNKNOWN
Classifier: Development Status :: 4 - Beta
Classifier: Environment :: Console
Classifier: Environment :: Web Environment
Classifier: Intended Audience :: Developers
Classifier: License :: OSI Approved :: GNU Library or Lesser General Public License (LGPL)
Classifier: Operating System :: POSIX
Classifier: Programming Language :: Python
Classifier: Topic :: Software Development :: Libraries
Classifier: Topic :: Internet :: WWW/HTTP :: Indexing/Search
Provides-Extra: dev
